setup.cfg
setup.py
streamshift/__init__.py
streamshift/app.py
streamshift/cli.py
streamshift/process.py
streamshift/stream.py
streamshift/util.py
streamshift.egg-info/PKG-INFO
streamshift.egg-info/SOURCES.txt
streamshift.egg-info/dependency_links.txt
streamshift.egg-info/entry_points.txt
streamshift.egg-info/requires.txt
streamshift.egg-info/top_level.txt
tests/__init__.py
tests/chunk_test.py
tests/stream_test.py