Metadata-Version: 1.0
Name: streamshift
Version: 0.0.9
Summary: Buffer audio streams and serve them back with a user-defined offset
Home-page: https://github.com/patyk/streamshift
Author: Gosha Sawicka
Author-email: mal.galazka@gmail.com
License: MIT
Keywords: radio audio stream
Platform: UNKNOWN
